testobject/__init__.py
testobject/client.py
testobject/devices.py
testobject/reports.py
testobject/storage.py
testobject/suites.py
testobject/watcher.py
testobject-1.0.0.post1.dist-info/LICENSE
testobject-1.0.0.post1.dist-info/METADATA
testobject-1.0.0.post1.dist-info/WHEEL
testobject-1.0.0.post1.dist-info/top_level.txt
testobject-1.0.0.post1.dist-info/RECORD
