Metadata-Version: 1.2
Name: testobject
Version: 1.0.0.post1
Summary: Python API wrapper for TestObject
Home-page: https://github.com/enriquegh/testobject-python-api
Author: Enrique Gonzalez
Author-email: egonzalezh94@gmail.com
License: MIT
Keywords: wrapper-api,testobject
Platform: UNKNOWN
Classifier: Development Status :: 4 - Beta
Classifier: Intended Audience :: Developers
Classifier: Topic :: Software Development :: Testing
Classifier: Programming Language :: Python
Classifier: Programming Language :: Python :: 3
Classifier: Programming Language :: Python :: 3.5
Classifier: Programming Language :: Python :: 3.7
Classifier: Programming Language :: Python :: Implementation :: CPython
Classifier: Programming Language :: Python :: Implementation :: PyPy
Classifier: Operating System :: OS Independent
Classifier: License :: OSI Approved :: MIT License
Requires-Python: >=3.5
